src/cli.py
src/db_handler.py
src/klb.py
src/utils.py
kook_live_bot-0.1.0.dist-info/LICENSE
kook_live_bot-0.1.0.dist-info/METADATA
kook_live_bot-0.1.0.dist-info/WHEEL
kook_live_bot-0.1.0.dist-info/entry_points.txt
kook_live_bot-0.1.0.dist-info/RECORD
