Metadata-Version: 2.1
Name: kook-live-bot
Version: 0.1.0
Summary: simple bot for push bili live status
License: MIT
Author: Noahlias
Author-email: yygggg@foxmail.com
Requires-Python: >=3.10,<4.0
Classifier: License :: OSI Approved :: MIT License
Classifier: Programming Language :: Python :: 3
Classifier: Programming Language :: Python :: 3.10
Classifier: Programming Language :: Python :: 3.11
Requires-Dist: bilireq (>=0.2.11,<0.3.0)
Requires-Dist: click (>=8.1.7,<9.0.0)
Requires-Dist: khl-py (>=0.3.16,<0.4.0)
Requires-Dist: loguru (>=0.7.2,<0.8.0)
Requires-Dist: python-dotenv (>=1.0.0,<2.0.0)
